LSRF_project/task2/saxl_lfsr.v
module s_axil #(
    parameter C_AXIL_ADDR_WIDTH = 4,
    parameter C_AXIL_DATA_WIDTH = 32
)(
    input aclk,
    input aresetn,

    // AXI-Lite Slave Interface
    input  [C_AXIL_ADDR_WIDTH-1:0] s_axi_awaddr,
    input                       s_axi_awvalid,
    output reg                  s_axi_awready,

    input  [C_AXIL_DATA_WIDTH-1:0] s_axi_wdata,
    input                       s_axi_wvalid,
    output reg                  s_axi_wready,

    output reg [1:0]            s_axi_bresp,
    output reg                  s_axi_bvalid,
    input                       s_axi_bready,

    input  [C_AXIL_ADDR_WIDTH-1:0] s_axi_araddr,
    input                       s_axi_arvalid,
    output reg                  s_axi_arready,

    output reg [C_AXIL_DATA_WIDTH-1:0] s_axi_rdata,
    output reg [1:0]            s_axi_rresp,
    output reg                  s_axi_rvalid,
    input                       s_axi_rready,

    // AXI - Stream Master Interface
    output reg [C_AXIL_DATA_WIDTH-1:0] m_axis_tdata,
    output reg                    m_axis_tvalid,
    input                         m_axis_tready
);

    // Address map for these registers
    // 0x00 - start_reg
    // 0x04 - stop_reg
    // 0x08 - seed_reg
    // 0x0C - taps_reg

    // Registers
    reg start_reg;
    reg stop_reg;
    reg [7:0] seed_reg;
    reg [7:0] taps_reg;
    reg feedback;
    
    // LFSR State Register
    reg [7:0] lfsr_reg;
    reg lfsr_active;
    reg lfsr_output_valid;
    
    // Register to store read address
    reg [C_AXIL_ADDR_WIDTH-1:0] axi_araddr;
    
    // FIX: Initialize the ready signals to prevent protocol freeze
    initial begin
        s_axi_awready = 1'b1;
        s_axi_wready = 1'b1;
        s_axi_arready = 1'b1;
    end
    
    // Write Address Channel - FIXED
    always @(posedge aclk or negedge aresetn) begin
        if (!aresetn) begin
            s_axi_awready <= 1'b1;  // Initialize to HIGH
        end else begin
            if (s_axi_awready && s_axi_awvalid) begin
                s_axi_awready <= 1'b0;  // Address received, deassert ready
            end else if (~s_axi_bvalid) begin
                s_axi_awready <= 1'b1;  // Ready for next transaction
            end
        end
    end
    
    // Write Data Channel - FIXED
    always @(posedge aclk or negedge aresetn) begin
        if (!aresetn) begin
            s_axi_wready <= 1'b1;  // Initialize to HIGH
            start_reg <= 1'b0;
            stop_reg <= 1'b0;
            seed_reg <= 8'h01;     // Default non-zero seed
            taps_reg <= 8'b10001110; // Default polynomial tap configuration
        end else begin
            if (s_axi_wready && s_axi_wvalid) begin
                s_axi_wready <= 1'b0;  // Data received, deassert ready
                
                // Write to the appropriate register based on address
                case (s_axi_awaddr[3:0])
                    4'h0: start_reg <= s_axi_wdata[0];
                    4'h4: stop_reg <= s_axi_wdata[0];
                    4'h8: seed_reg <= s_axi_wdata[7:0];
                    4'hC: taps_reg <= s_axi_wdata[7:0];
                    default: begin
                        // No register to write to
                    end
                endcase
            end else if (~s_axi_bvalid) begin
                s_axi_wready <= 1'b1;  // Ready for next transaction
            end
        end
    end
    
    // Write Response Channel - FIXED
    always @(posedge aclk or negedge aresetn) begin
        if (!aresetn) begin
            s_axi_bvalid <= 1'b0;
            s_axi_bresp <= 2'b0;
        end else begin
            if (~s_axi_awready && ~s_axi_wready && ~s_axi_bvalid) begin
                // Both address and data received, generate response
                s_axi_bvalid <= 1'b1;
                s_axi_bresp <= 2'b00;  // OKAY response
            end else if (s_axi_bvalid && s_axi_bready) begin
                // Response accepted by master
                s_axi_bvalid <= 1'b0;
            end
        end
    end
    
    // Read Address Channel - FIXED
    always @(posedge aclk or negedge aresetn) begin
        if (!aresetn) begin
            s_axi_arready <= 1'b1;  // Initially ready for read address
            axi_araddr <= 0;
        end else begin
            if (s_axi_arready && s_axi_arvalid) begin
                axi_araddr <= s_axi_araddr;  // Capture the read address
                s_axi_arready <= 1'b0;       // Not ready for next address yet
            end else if (s_axi_rvalid && s_axi_rready) begin
                s_axi_arready <= 1'b1;       // Ready for next read address after current read completes
            end
        end
    end
    
    // Read Data Channel - FIXED
    always @(posedge aclk or negedge aresetn) begin
        if (!aresetn) begin
            s_axi_rvalid <= 1'b0;
            s_axi_rresp <= 2'b00;
            s_axi_rdata <= {C_AXIL_DATA_WIDTH{1'b0}};
        end else begin
            if (~s_axi_arready && ~s_axi_rvalid) begin
                s_axi_rvalid <= 1'b1;        // Assert valid when we have address data
                s_axi_rresp <= 2'b00;        // OKAY response
                
                // Read from registers based on captured address
                case (axi_araddr[3:0])
                    4'h0: s_axi_rdata <= {31'b0, start_reg};
                    4'h4: s_axi_rdata <= {31'b0, stop_reg};
                    4'h8: s_axi_rdata <= {24'b0, seed_reg};
                    4'hC: s_axi_rdata <= {24'b0, taps_reg};
                    default: s_axi_rdata <= 32'hDEADBEEF; // Return error value for debug
                endcase
            end else if (s_axi_rvalid && s_axi_rready) begin
                s_axi_rvalid <= 1'b0;        // Clear valid after handshake completes
            end
        end
    end
    
    // LFSR control logic
    always @(posedge aclk or negedge aresetn) begin
        if (!aresetn) begin
            lfsr_reg <= 8'h0;
            lfsr_active <= 1'b0;
            lfsr_output_valid <= 1'b0;
        end else begin
            // Ensure LFSR starts with the correct seed
            if (start_reg && !stop_reg && !lfsr_active) begin
                lfsr_reg <= seed_reg; // Load seed when starting
                lfsr_active <= 1'b1;
                lfsr_output_valid <= 1'b1;
            end else if (stop_reg) begin
                lfsr_active <= 1'b0;
                lfsr_output_valid <= 1'b0;
            end
            
            // If LFSR is active, generate next value
            if (lfsr_active && m_axis_tready) begin
                feedback = ^(lfsr_reg & taps_reg); // XOR taps
                lfsr_reg <= {lfsr_reg[6:0], feedback}; // Shift LFSR
                lfsr_output_valid <= 1'b1;
            end else begin
                lfsr_output_valid <= lfsr_active;
            end
        end
    end
    
    // AXI-Stream Master logic
    always @(posedge aclk or negedge aresetn) begin
        if (!aresetn) begin
            m_axis_tvalid <= 1'b0;
            m_axis_tdata <= 32'h0;
        end else begin
            if (lfsr_output_valid && m_axis_tready) begin
                m_axis_tdata <= {24'h0, lfsr_reg};
                m_axis_tvalid <= 1'b1;
            end else if (m_axis_tready) begin
                m_axis_tvalid <= 1'b0;
            end
        end
    end

endmodule

LSRF_task_2/task1/system_tb.v
`timescale 1ns / 1ps

module s_axil_tb;

    reg aclk;
    reg aresetn;

    // AXI-Lite Write Address Channel
    reg [3:0] s_axi_awaddr;
    reg s_axi_awvalid;
    wire s_axi_awready;

    // AXI-Lite Write Data Channel
    reg [31:0] s_axi_wdata;
    reg s_axi_wvalid;
    wire s_axi_wready;

    // AXI-Lite Write Response Channel
    wire [1:0] s_axi_bresp;
    wire s_axi_bvalid;
    reg s_axi_bready;

    // AXI-Lite Read Address Channel
    reg [3:0] s_axi_araddr;
    reg s_axi_arvalid;
    wire s_axi_arready;

    // AXI-Lite Read Data Channel
    wire [31:0] s_axi_rdata;
    wire [1:0] s_axi_rresp;
    wire s_axi_rvalid;
    reg s_axi_rready;

    // AXI-Stream signals
    wire [31:0] m_axis_tdata;
    wire m_axis_tvalid;
    reg m_axis_tready;

    // Instantiate DUT
    s_axil dut (
        .aclk(aclk),
        .aresetn(aresetn),
        .s_axi_awaddr(s_axi_awaddr),
        .s_axi_awvalid(s_axi_awvalid),
        .s_axi_awready(s_axi_awready),
        .s_axi_wdata(s_axi_wdata),
        .s_axi_wvalid(s_axi_wvalid),
        .s_axi_wready(s_axi_wready),
        .s_axi_bresp(s_axi_bresp),
        .s_axi_bvalid(s_axi_bvalid),
        .s_axi_bready(s_axi_bready),
        .s_axi_araddr(s_axi_araddr),
        .s_axi_arvalid(s_axi_arvalid),
        .s_axi_arready(s_axi_arready),
        .s_axi_rdata(s_axi_rdata),
        .s_axi_rresp(s_axi_rresp),
        .s_axi_rvalid(s_axi_rvalid),
        .s_axi_rready(s_axi_rready),
        .m_axis_tdata(m_axis_tdata),
        .m_axis_tvalid(m_axis_tvalid),
        .m_axis_tready(m_axis_tready)
    );

    // Clock generation
    always #5 aclk = ~aclk;

    // Task for AXI Write Operation - SIMPLIFIED and FIXED
    task axi_write(input [3:0] addr, input [31:0] data);
        begin
            // Setup phase
            @(posedge aclk);
            s_axi_awaddr = addr;
            s_axi_awvalid = 1'b1;
            s_axi_wdata = data;
            s_axi_wvalid = 1'b1;
            s_axi_bready = 1'b1;
            
            // Wait for address and data to be accepted
            while (!(s_axi_awready && s_axi_wready)) @(posedge aclk);
            
            // Address and data accepted
            @(posedge aclk);
            s_axi_awvalid = 1'b0;
            s_axi_wvalid = 1'b0;
            
            // Wait for response
            while (!s_axi_bvalid) @(posedge aclk);
            
            // Complete transaction
            @(posedge aclk);
            s_axi_bready = 1'b0;
            
            // Gap between transactions
            @(posedge aclk);
            @(posedge aclk);
        end
    endtask

    // Task for AXI Read Operation - SIMPLIFIED and FIXED
    task axi_read(input [3:0] addr);
        begin
            // Setup phase
            @(posedge aclk);
            s_axi_araddr = addr;
            s_axi_arvalid = 1'b1;
            s_axi_rready = 1'b0;
            
            // Wait for address to be accepted
            while (!s_axi_arready) @(posedge aclk);
            
            // Address accepted
            @(posedge aclk);
            s_axi_arvalid = 1'b0;
            s_axi_rready = 1'b1;
            
            // Wait for data
            while (!s_axi_rvalid) @(posedge aclk);
            
            // Display read data
            $display("Read from address 0x%0h: 0x%0h", addr, s_axi_rdata);
            
            // Complete transaction
            @(posedge aclk);
            s_axi_rready = 1'b0;
            
            // Gap between transactions
            @(posedge aclk);
            @(posedge aclk);
        end
    endtask

    // Test Sequence
    initial begin
        // Initialize signals
        aclk = 0;
        aresetn = 0;
        s_axi_awaddr = 0;
        s_axi_awvalid = 0;
        s_axi_wdata = 0;
        s_axi_wvalid = 0;
        s_axi_bready = 0;
        s_axi_araddr = 0;
        s_axi_arvalid = 0;
        s_axi_rready = 0;
        m_axis_tready = 1;

        // Dump file for waveform viewing
        $dumpfile("s_axil_tb.vcd");
        $dumpvars(0, s_axil_tb);

        // Reset sequence
        repeat(5) @(posedge aclk);
        aresetn = 1;
        repeat(2) @(posedge aclk);

        // Debug message
        $display("Starting AXI-Lite Test Sequence");
        
        // 1️⃣ Write seed value (Register @ 0x8)
        $display("\nWriting seed value 0xA5 to register 0x8");
        axi_write(4'h8, 32'h000000A5);
        $display("Seed register write completed");

        // 2️⃣ Write taps value (Register @ 0xC)
        $display("\nWriting taps value 0xB8 to register 0xC");
        axi_write(4'hC, 32'h000000B8);
        $display("Taps register write completed");

        // 3️⃣ Read back seed value (Register @ 0x8)
        $display("\nReading back seed value from register 0x8");
        axi_read(4'h8);

        // 4️⃣ Read back taps value (Register @ 0xC)
        $display("\nReading back taps value from register 0xC");
        axi_read(4'hC);

        // 5️⃣ Start LFSR (Control Register @ 0x0)
        $display("\nStarting LFSR by writing 1 to register 0x0");
        axi_write(4'h0, 32'h00000001);
        $display("LFSR start command sent");

        // 6️⃣ Read back control register (Register @ 0x0)
        $display("\nReading back control register 0x0");
        axi_read(4'h0);

        // Wait for LFSR outputs
        $display("\nWaiting for LFSR outputs...");
        repeat(10) @(posedge aclk);

        // 7️⃣ Stop LFSR (Control Register @ 0x4)
        $display("\nStopping LFSR by writing 1 to register 0x4");
        axi_write(4'h4, 32'h00000001);
        $display("LFSR stop command sent");

        // 8️⃣ Read back stop register (Register @ 0x4)
        $display("\nReading back stop register 0x4");
        axi_read(4'h4);

        // Final wait
        $display("\nTest complete");
        repeat(10) @(posedge aclk);
        $finish;
    end

    // Debug monitor for LFSR outputs
    initial begin
        forever begin
            @(posedge aclk);
            if (m_axis_tvalid && m_axis_tready) begin
                $display("LFSR Output: 0x%0h at time %0t", m_axis_tdata, $time);
            end
        end
    end

endmodule

LSRF_project/task1/s_axil_tb.vcd
$date
	Thu Apr 03 01:44:18 2025
$end
$version
	Icarus Verilog
$end
$timescale
	1ps
$end
$scope module s_axil_tb $end
$var wire 1 ! s_axi_wready $end
$var wire 1 " s_axi_rvalid $end
$var wire 2 # s_axi_rresp [1:0] $end
$var wire 32 $ s_axi_rdata [31:0] $end
$var wire 1 % s_axi_bvalid $end
$var wire 2 & s_axi_bresp [1:0] $end
$var wire 1 ' s_axi_awready $end
$var wire 1 ( s_axi_arready $end
$var wire 1 ) m_axis_tvalid $end
$var wire 32 * m_axis_tdata [31:0] $end
$var reg 1 + aclk $end
$var reg 1 , aresetn $end
$var reg 1 - m_axis_tready $end
$var reg 4 . s_axi_araddr [3:0] $end
$var reg 1 / s_axi_arvalid $end
$var reg 4 0 s_axi_awaddr [3:0] $end
$var reg 1 1 s_axi_awvalid $end
$var reg 1 2 s_axi_bready $end
$var reg 1 3 s_axi_rready $end
$var reg 32 4 s_axi_wdata [31:0] $end
$var reg 1 5 s_axi_wvalid $end
$scope module dut $end
$var wire 1 + aclk $end
$var wire 1 , aresetn $end
$var wire 1 - m_axis_tready $end
$var wire 4 6 s_axi_araddr [3:0] $end
$var wire 1 / s_axi_arvalid $end
$var wire 4 7 s_axi_awaddr [3:0] $end
$var wire 1 1 s_axi_awvalid $end
$var wire 1 2 s_axi_bready $end
$var wire 1 3 s_axi_rready $end
$var wire 32 8 s_axi_wdata [31:0] $end
$var wire 1 5 s_axi_wvalid $end
$var parameter 32 9 C_AXIL_ADDR_WIDTH $end
$var parameter 32 : C_AXIL_DATA_WIDTH $end
$var reg 4 ; axi_araddr [3:0] $end
$var reg 1 < feedback $end
$var reg 1 = lfsr_active $end
$var reg 1 > lfsr_output_valid $end
$var reg 8 ? lfsr_reg [7:0] $end
$var reg 32 @ m_axis_tdata [31:0] $end
$var reg 1 ) m_axis_tvalid $end
$var reg 1 ( s_axi_arready $end
$var reg 1 ' s_axi_awready $end
$var reg 2 A s_axi_bresp [1:0] $end
$var reg 1 % s_axi_bvalid $end
$var reg 32 B s_axi_rdata [31:0] $end
$var reg 2 C s_axi_rresp [1:0] $end
$var reg 1 " s_axi_rvalid $end
$var reg 1 ! s_axi_wready $end
$var reg 8 D seed_reg [7:0] $end
$var reg 1 E start_reg $end
$var reg 1 F stop_reg $end
$var reg 8 G taps_reg [7:0] $end
$upscope $end
$scope task axi_read $end
$var reg 4 H addr [3:0] $end
$upscope $end
$scope task axi_write $end
$var reg 4 I addr [3:0] $end
$var reg 32 J data [31:0] $end
$upscope $end
$upscope $end
$enddefinitions $end
$comment Show the parameter values. $end
$dumpall
b100000 :
b100 9
$end
#0
$dumpvars
bx J
bx I
bx H
b10001110 G
0F
0E
b1 D
b0 C
b0 B
b0 A
b0 @
b0 ?
0>
0=
x<
b0 ;
b0 8
b0 7
b0 6
05
b0 4
03
02
01
b0 0
0/
b0 .
1-
0,
0+
b0 *
0)
1(
1'
b0 &
0%
b0 $
b0 #
0"
1!
$end
#5000
1+
#10000
0+
#15000
1+
#20000
0+
#25000
1+
#30000
0+
#35000
1+
#40000
0+
#45000
1,
1+
#50000
0+
#55000
1+
#60000
0+
#65000
b10100101 J
b1000 I
1+
#70000
0+
#75000
0'
b10100101 D
0!
12
15
b10100101 4
b10100101 8
11
b1000 0
b1000 7
1+
#80000
0+
#85000
1%
1!
1'
05
01
1+
#90000
0+
#95000
0%
1+
#100000
0+
#105000
02
1+
#110000
0+
#115000
1+
#120000
0+
#125000
b10111000 J
b1100 I
1+
#130000
0+
#135000
0'
b10111000 G
0!
12
15
b10111000 4
b10111000 8
11
b1100 0
b1100 7
1+
#140000
0+
#145000
1%
1!
1'
05
01
1+
#150000
0+
#155000
0%
1+
#160000
0+
#165000
02
1+
#170000
0+
#175000
1+
#180000
0+
#185000
b1000 H
1+
#190000
0+
#195000
0(
b1000 ;
1/
b1000 .
b1000 6
1+
#200000
0+
#205000
b10100101 $
b10100101 B
1"
13
0/
1+
#210000
0+
#215000
1(
0"
1+
#220000
0+
#225000
03
1+
#230000
0+
#235000
1+
#240000
0+
#245000
b1100 H
1+
#250000
0+
#255000
0(
b1100 ;
1/
b1100 .
b1100 6
1+
#260000
0+
#265000
b10111000 $
b10111000 B
1"
13
0/
1+
#270000
0+
#275000
1(
0"
1+
#280000
0+
#285000
03
1+
#290000
0+
#295000
1+
#300000
0+
#305000
b1 J
b0 I
1+
#310000
0+
#315000
0'
1E
0!
12
15
b1 4
b1 8
11
b0 0
b0 7
1+
#320000
0+
#325000
0>
1=
b10100101 ?
1%
1!
1'
05
01
1+
#330000
0+
#335000
0%
1>
b1001010 ?
0<
1+
#340000
0+
#345000
1)
b1001010 *
b1001010 @
b10010101 ?
1<
02
1+
#350000
0+
#355000
b101010 ?
b10010101 *
b10010101 @
0<
1+
#360000
0+
#365000
b101010 *
b101010 @
b1010100 ?
b0 H
1+
#370000
0+
#375000
0(
b0 ;
b10101001 ?
b1010100 *
b1010100 @
1<
1/
b0 .
b0 6
1+
#380000
0+
#385000
b10101001 *
b10101001 @
b1010011 ?
b1 $
b1 B
1"
13
0/
1+
#390000
0+
#395000
1(
0"
b10100111 ?
b1010011 *
b1010011 @
1+
#400000
0+
#405000
b10100111 *
b10100111 @
b1001110 ?
0<
03
1+
#410000
0+
#415000
b10011101 ?
b1001110 *
b1001110 @
1<
1+
#420000
0+
#425000
b10011101 *
b10011101 @
b111011 ?
1+
#430000
0+
#435000
b1110111 ?
b111011 *
b111011 @
1+
#440000
0+
#445000
b1110111 *
b1110111 @
b11101110 ?
0<
1+
#450000
0+
#455000
b11011101 ?
b11101110 *
b11101110 @
1<
1+
#460000
0+
#465000
b11011101 *
b11011101 @
b10111011 ?
1+
#470000
0+
#475000
b1110110 ?
b10111011 *
b10111011 @
0<
1+
#480000
0+
#485000
b1110110 *
b1110110 @
b11101100 ?
1+
#490000
0+
#495000
b11011001 ?
b11101100 *
b11101100 @
1<
1+
#500000
0+
#505000
b11011001 *
b11011001 @
b10110011 ?
1+
#510000
0+
#515000
b1100111 ?
b10110011 *
b10110011 @
1+
#520000
0+
#525000
b1100111 *
b1100111 @
b11001111 ?
b100 I
1+
#530000
0+
#535000
0'
1F
0!
b10011110 ?
b11001111 *
b11001111 @
0<
12
15
11
b100 0
b100 7
1+
#540000
0+
#545000
b10011110 *
b10011110 @
b111101 ?
1>
0=
1%
1!
1'
1<
05
01
1+
#550000
0+
#555000
0%
0>
b111101 *
b111101 @
1+
#560000
0+
#565000
0)
02
1+
#570000
0+
#575000
1+
#580000
0+
#585000
b100 H
1+
#590000
0+
#595000
0(
b100 ;
1/
b100 .
b100 6
1+
#600000
0+
#605000
1"
13
0/
1+
#610000
0+
#615000
1(
0"
1+
#620000
0+
#625000
03
1+
